landing_cloner/__init__.py
landing_cloner/cli.py
landing_cloner/server_builder.py
landing_cloner/url2file.py
landing_cloner/utils.py
landing_cloner-0.1.0.dist-info/licenses/LICENSE
landing_cloner-0.1.0.dist-info/METADATA
landing_cloner-0.1.0.dist-info/WHEEL
landing_cloner-0.1.0.dist-info/entry_points.txt
landing_cloner-0.1.0.dist-info/top_level.txt
landing_cloner-0.1.0.dist-info/RECORD
